{"edoc": "{\"guid\": \"6d8b4395-1f3a-4023-ae35-7de58ead008d\",\"liveboard\": {\"name\": \"Live5\",\"visualizations\": [{\"id\": \"Viz_1\",\"answer\": {\"name\": \"Total HIGH_END_OF_RANGE by PLANT_NAME\",\"tables\": [{\"id\": \"VEGETABLE\",\"name\": \"VEGETABLE\"}],\"search_query\": \"[PLANT_NAME] [HIGH_END_OF_RANGE]\",\"answer_columns\": [{\"name\": \"PLANT_NAME\"},{\"name\": \"Total HIGH_END_OF_RANGE\"}],\"table\": {\"table_columns\": [{\"column_id\": \"PLANT_NAME\",\"show_headline\": false},{\"column_id\": \"Total HIGH_END_OF_RANGE\",\"show_headline\": false}],\"ordered_column_ids\": [\"PLANT_NAME\",\"Total HIGH_END_OF_RANGE\"],\"client_state\": \"\",\"client_state_v2\": \"{\\\"tableVizPropVersion\\\": \\\"V1\\\"}\"},\"chart\": {\"type\": \"COLUMN\",\"chart_columns\": [{\"column_id\": \"PLANT_NAME\"},{\"column_id\": \"Total HIGH_END_OF_RANGE\"}],\"axis_configs\": [{\"x\": [\"PLANT_NAME\"],\"y\": [\"Total HIGH_END_OF_RANGE\"]}],\"client_state\": \"\",\"client_state_v2\": \"{\\\"version\\\": \\\"V4DOT2\\\",\\\"chartProperties\\\": {\\\"responsiveLayoutPreference\\\": \\\"AUTO_ON\\\",\\\"chartSpecific\\\": {}},\\\"columnProperties\\\": [{\\\"columnId\\\": \\\"PLANT_NAME\\\",\\\"columnProperty\\\": {}},{\\\"columnId\\\": \\\"Total HIGH_END_OF_RANGE\\\",\\\"columnProperty\\\": {}}],\\\"axisProperties\\\": [{\\\"id\\\": \\\"7486d434-1ba1-4a41-a2c5-82660d3202e8\\\",\\\"properties\\\": {\\\"axisType\\\": \\\"Y\\\",\\\"linkedColumns\\\": [\\\"Total HIGH_END_OF_RANGE\\\"],\\\"isOpposite\\\": false}},{\\\"id\\\": \\\"de3d3a67-05a7-4648-a3e6-e91a10605e81\\\",\\\"properties\\\": {\\\"axisType\\\": \\\"X\\\",\\\"linkedColumns\\\": [\\\"PLANT_NAME\\\"]}}],\\\"systemSeriesColors\\\": [{\\\"serieName\\\": \\\"Total HIGH_END_OF_RANGE\\\",\\\"color\\\": \\\"#48D1E0\\\"}]}\"},\"display_mode\": \"CHART_MODE\"},\"viz_guid\": \"69ac4557-a666-414e-a53f-aaaf7b6fc8c9\"}]}}", "info": {"filename": "Live5.liveboard.tml", "name": "Live5", "id": "6d8b4395-1f3a-4023-ae35-7de58ead008d", "type": "liveboard", "status": {"status_code": "OK"}}}